fastparquet/__init__.py
fastparquet/_version.py
fastparquet/api.py
fastparquet/cencoding.c
fastparquet/cencoding.cpython-314-i386-linux-gnu.so
fastparquet/cencoding.pyx
fastparquet/compression.py
fastparquet/converted_types.py
fastparquet/core.py
fastparquet/dataframe.py
fastparquet/encoding.py
fastparquet/evolve.py
fastparquet/json.py
fastparquet/parquet.thrift
fastparquet/schema.py
fastparquet/speedups.c
fastparquet/speedups.cpython-314-i386-linux-gnu.so
fastparquet/speedups.pyx
fastparquet/thrift_structures.py
fastparquet/util.py
fastparquet/writer.py
fastparquet/parquet_thrift/__init__.py
fastparquet/parquet_thrift/parquet/__init__.py
fastparquet/parquet_thrift/parquet/ttypes.py
fastparquet-2025.12.0.dist-info/METADATA
fastparquet-2025.12.0.dist-info/WHEEL
fastparquet-2025.12.0.dist-info/top_level.txt
fastparquet-2025.12.0.dist-info/RECORD
fastparquet-2025.12.0.dist-info/licenses/LICENSE
